lazyimport/__init__.py
lazyimport/lazy_import.py
typed_lazyimport-0.3.1.dist-info/LICENSE
typed_lazyimport-0.3.1.dist-info/METADATA
typed_lazyimport-0.3.1.dist-info/WHEEL
typed_lazyimport-0.3.1.dist-info/RECORD
