Metadata-Version: 2.1
Name: typed-lazyimport
Version: 0.3.1
Summary: Provides type hinted lazy import for slow to load libraries
Home-page: https://github.com/jojje/typed-lazyimport
License: MIT
Keywords: lazy,import
Author: jojje
Author-email: tinjon+pypi@gmail.com
Requires-Python: >=3.8.1,<4.0.0
Classifier: Development Status :: 4 - Beta
Classifier: License :: OSI Approved :: MIT License
Classifier: Operating System :: MacOS
Classifier: Operating System :: Microsoft :: Windows
Classifier: Operating System :: POSIX :: Linux
Classifier: Programming Language :: Python :: 3
Classifier: Programming Language :: Python :: 3.9
Classifier: Programming Language :: Python :: 3.10
Classifier: Programming Language :: Python :: 3.11
Classifier: Programming Language :: Python :: 3.12
Classifier: Topic :: Software Development :: Libraries
Project-URL: Bug Tracker, https://github.com/jojje/typed-lazyimport/issues
